pi3/__init__.py
pi3/switch.py
pi3_switch-0.5.2.data/scripts/switch.py
pi3_switch-0.5.2.dist-info/METADATA
pi3_switch-0.5.2.dist-info/RECORD
pi3_switch-0.5.2.dist-info/WHEEL
pi3_switch-0.5.2.dist-info/entry_points.txt
pi3_switch-0.5.2.dist-info/top_level.txt
pi3_switch-0.5.2.dist-info/zip-safe
