Metadata-Version: 2.1
Name: pi3-switch
Version: 0.5.2
Summary: More advanced workspace switcher for i3.
Home-page: https://github.com/Landmaj/pi3-switch
Author: Michał Wieluński
Author-email: michal@landmaj.pl
License: MIT
Platform: UNKNOWN
Classifier: Development Status :: 4 - Beta
Classifier: License :: OSI Approved :: MIT License
Classifier: Operating System :: POSIX :: Linux
Classifier: Programming Language :: Python :: 3
Classifier: Topic :: Desktop Environment :: Window Managers
Requires-Dist: i3ipc (==1.5.1)
Requires-Dist: pynput (==1.2)
